pishock/__init__.py
pishock/firmwareupdate.py
pishock/zap/core.py
pishock/zap/httpapi.py
pishock/zap/serialapi.py
pishock/zap/cli/cli.py
pishock/zap/cli/cli_code.py
pishock/zap/cli/cli_random.py
pishock/zap/cli/cli_serial.py
pishock/zap/cli/cli_utils.py
pishock-1.2.1.dist-info/METADATA
pishock-1.2.1.dist-info/WHEEL
pishock-1.2.1.dist-info/entry_points.txt
pishock-1.2.1.dist-info/RECORD
