Metadata-Version: 2.4
Name: pishock
Version: 1.2.1
Summary: The bestest Python PiShock API wrapper and CLI!
Project-URL: Documentation, https://python-pishock.readthedocs.io/
Project-URL: Repository, https://github.com/zerario/Python-PiShock
Project-URL: Issues, https://github.com/zerario/Python-PiShock/issues
Project-URL: Changelog, https://python-pishock.readthedocs.io/en/latest/changelog.html
Author-email: Zerario <derg@zerario.dev>
Requires-Python: <3.15,>=3.9
Requires-Dist: platformdirs>=4.3.8
Requires-Dist: pyserial>=3.5
Requires-Dist: requests>=2.32.3
Requires-Dist: rich>=14.0.0
Requires-Dist: typer>=0.16.0
Requires-Dist: typing-extensions>=4.13.2
